{"00530000000000001ea9":{"cluster_role_mapped":"Bare","best_soft_norm":0.7198649381368671,"uncertain":false,"flipped_this_season":false,"streak_len_current":3,"time_since_last_flip":null,"npts_total":5,"env_z_season":-0.7068577443724986,"stratum":"Mid","confidence_bucket":null},"00530000000000001eab":{"cluster_role_mapped":"Bare","best_soft_norm":0.0,"uncertain":true,"flipped_this_season":false,"streak_len_current":3,"time_since_last_flip":null,"npts_total":5,"env_z_season":-0.928203044462034,"stratum":"Mid","confidence_bucket":null},"00530000000000001ead":{"cluster_role_mapped":"Bare","best_soft_norm":0.9237539042156205,"uncertain":false,"flipped_this_season":false,"streak_len_current":3,"time_since_last_flip":null,"npts_total":5,"env_z_season":-0.0744346213974637,"stratum":"Mid","confidence_bucket":null},"00530000000000001eae":{"cluster_role_mapped":"Bare","best_soft_norm":0.8212093363612509,"uncertain":false,"flipped_this_season":false,"streak_len_current":3,"time_since_last_flip":null,"npts_total":5,"env_z_season":0.029867095998114983,"stratum":"Mid","confidence_bucket":null},"00530000000000001eaf":{"cluster_role_mapped":"Bare","best_soft_norm":0.8352789303648356,"uncertain":false,"flipped_this_season":false,"streak_len_current":3,"time_since_last_flip":null,"npts_total":5,"env_z_season":0.011902350496479608,"stratum":"Mid","confidence_bucket":null},"00530000000000001eb0":{"cluster_role_mapped":"Bare","best_soft_norm":0.969854533629723,"uncertain":false,"flipped_this_season":false,"streak_len_current":3,"time_since_last_flip":null,"npts_total":5,"env_z_season":-0.19460579158534239,"stratum":"Mid","confidence_bucket":null},"00530000000000001eb1":{"cluster_role_mapped":"Cover","best_soft_norm":0.2041837517291644,"uncertain":false,"flipped_this_season":false,"streak_len_current":2,"time_since_last_flip":1,"npts_total":5,"env_z_season":0.40128925310518315,"stratum":"Mid","confidence_bucket":null},"00530000000000001eb2":{"cluster_role_mapped":"Cover","best_soft_norm":0.1293965505644514,"uncertain":true,"flipped_this_season":false,"streak_len_current":2,"time_since_last_flip":1,"npts_total":5,"env_z_season":-0.07310679560270077,"stratum":"Mid","confidence_bucket":null},"00530000000000001eb4":{"cluster_role_mapped":"Cover","best_soft_norm":0.37575835851730416,"uncertain":false,"flipped_this_season":false,"streak_len_current":2,"time_since_last_flip":1,"npts_total":5,"env_z_season":0.35159297307606524,"stratum":"Mid","confidence_bucket":null},"00530000000000001eb5":{"cluster_role_mapped":"Cover","best_soft_norm":0.3610343938001,"uncertain":false,"flipped_this_season":false,"streak_len_current":2,"time_since_last_flip":1,"npts_total":5,"env_z_season":0.3593976340230224,"stratum":"Mid","confidence_bucket":null},"00530000000000001eb7":{"cluster_role_mapped":"Bare","best_soft_norm":1.0,"uncertain":false,"flipped_this_season":false,"streak_len_current":2,"time_since_last_flip":1,"npts_total":5,"env_z_season":-0.193985523910581,"stratum":"Mid","confidence_bucket":null},"00530000000000001eb8":{"cluster_role_mapped":"Bare","best_soft_norm":0.8841008161945592,"uncertain":false,"flipped_this_season":false,"streak_len_current":3,"time_since_last_flip":null,"npts_total":5,"env_z_season":0.0,"stratum":"Mid","confidence_bucket":null},"00530000000000001eb9":{"cluster_role_mapped":"Bare","best_soft_norm":0.6077459558142595,"uncertain":false,"flipped_this_season":false,"streak_len_current":3,"time_since_last_flip":null,"npts_total":5,"env_z_season":0.18899639451792952,"stratum":"Mid","confidence_bucket":null},"00530000000000001eba":{"cluster_role_mapped":"Bare","best_soft_norm":0.5791988438445039,"uncertain":false,"flipped_this_season":false,"streak_len_current":3,"time_since_last_flip":null,"npts_total":5,"env_z_season":-0.6011599770117069,"stratum":"Mid","confidence_bucket":null},"00530000000000001ebb":{"cluster_role_mapped":"Bare","best_soft_norm":0.11162756365368197,"uncertain":true,"flipped_this_season":false,"streak_len_current":2,"time_since_last_flip":1,"npts_total":5,"env_z_season":0.5670454953244901,"stratum":"Mid","confidence_bucket":null},"00530000000000001ebc":{"cluster_role_mapped":"Bare","best_soft_norm":0.0,"uncertain":true,"flipped_this_season":false,"streak_len_current":3,"time_since_last_flip":null,"npts_total":5,"env_z_season":0.5030716847695471,"stratum":"Mid","confidence_bucket":null},"00530000000000001ebd":{"cluster_role_mapped":"Bare","best_soft_norm":0.0,"uncertain":true,"flipped_this_season":true,"streak_len_current":1,"time_since_last_flip":0,"npts_total":5,"env_z_season":0.3296032978707392,"stratum":"Mid","confidence_bucket":null},"00530000000000001ebe":{"cluster_role_mapped":"Bare","best_soft_norm":0.7742329454779103,"uncertain":false,"flipped_this_season":false,"streak_len_current":2,"time_since_last_flip":1,"npts_total":5,"env_z_season":-0.4035564877108942,"stratum":"Mid","confidence_bucket":null},"00530000000000001ec0":{"cluster_role_mapped":"Cover","best_soft_norm":0.2194676180896657,"uncertain":false,"flipped_this_season":true,"streak_len_current":1,"time_since_last_flip":0,"npts_total":5,"env_z_season":1.527281653397426,"stratum":"Mid","confidence_bucket":null},"00530000000000001ec1":{"cluster_role_mapped":"Cover","best_soft_norm":0.6830077445361249,"uncertain":false,"flipped_this_season":false,"streak_len_current":3,"time_since_last_flip":null,"npts_total":5,"env_z_season":1.1961324995375675,"stratum":"Mid","confidence_bucket":null},"00530000000000001ec3":{"cluster_role_mapped":"Bare","best_soft_norm":0.35275065150466256,"uncertain":false,"flipped_this_season":false,"streak_len_current":3,"time_since_last_flip":null,"npts_total":5,"env_z_season":-1.7883144193503144,"stratum":"Mid","confidence_bucket":null},"00530000000000001ec4":{"cluster_role_mapped":"Bare","best_soft_norm":0.5219352439140132,"uncertain":false,"flipped_this_season":false,"streak_len_current":3,"time_since_last_flip":null,"npts_total":5,"env_z_season":-1.177649274009706,"stratum":"Mid","confidence_bucket":null},"00530000000000001ec8":{"cluster_role_mapped":"Cover","best_soft_norm":0.5484597432014621,"uncertain":false,"flipped_this_season":true,"streak_len_current":1,"time_since_last_flip":0,"npts_total":5,"env_z_season":1.9669595081535713,"stratum":"Mid","confidence_bucket":null},"005300000000000022e1":{"cluster_role_mapped":"Bare","best_soft_norm":0.9506296689971901,"uncertain":false,"flipped_this_season":false,"streak_len_current":3,"time_since_last_flip":null,"npts_total":5,"env_z_season":0.01905368167165253,"stratum":"Mid","confidence_bucket":null},"005300000000000022e2":{"cluster_role_mapped":"Bare","best_soft_norm":0.8999967803466447,"uncertain":false,"flipped_this_season":false,"streak_len_current":3,"time_since_last_flip":null,"npts_total":5,"env_z_season":-0.6176929515206026,"stratum":"Mid","confidence_bucket":null},"005300000000000022e3":{"cluster_role_mapped":"Cover","best_soft_norm":0.41924132294669886,"uncertain":false,"flipped_this_season":false,"streak_len_current":2,"time_since_last_flip":1,"npts_total":5,"env_z_season":0.3825935594485924,"stratum":"Mid","confidence_bucket":null},"005300000000000022e4":{"cluster_role_mapped":"Cover","best_soft_norm":0.19458207642878947,"uncertain":false,"flipped_this_season":false,"streak_len_current":3,"time_since_last_flip":null,"npts_total":5,"env_z_season":1.3769867925661654,"stratum":"Mid","confidence_bucket":null},"00530000000000002410":{"cluster_role_mapped":"Cover","best_soft_norm":0.041412172606181324,"uncertain":true,"flipped_this_season":false,"streak_len_current":2,"time_since_last_flip":1,"npts_total":5,"env_z_season":1.4724877132894547,"stratum":"Mid","confidence_bucket":null},"00530000000000002414":{"cluster_role_mapped":"Bare","best_soft_norm":0.4729569161767264,"uncertain":false,"flipped_this_season":true,"streak_len_current":1,"time_since_last_flip":0,"npts_total":5,"env_z_season":-1.1301666378469948,"stratum":"Mid","confidence_bucket":null},"00530000000000002416":{"cluster_role_mapped":"Bare","best_soft_norm":0.2752129932622442,"uncertain":false,"flipped_this_season":false,"streak_len_current":3,"time_since_last_flip":null,"npts_total":5,"env_z_season":0.37139076300041685,"stratum":"Mid","confidence_bucket":null},"00530000000000002417":{"cluster_role_mapped":"Bare","best_soft_norm":0.5796886997163379,"uncertain":false,"flipped_this_season":false,"streak_len_current":3,"time_since_last_flip":null,"npts_total":5,"env_z_season":-1.1215656304797417,"stratum":"Mid","confidence_bucket":null},"00530000000000002418":{"cluster_role_mapped":"Bare","best_soft_norm":0.20351211174095155,"uncertain":false,"flipped_this_season":false,"streak_len_current":3,"time_since_last_flip":null,"npts_total":5,"env_z_season":0.17571886240882265,"stratum":"Mid","confidence_bucket":null},"00530000000000002419":{"cluster_role_mapped":"Bare","best_soft_norm":0.9778041678799063,"uncertain":false,"flipped_this_season":false,"streak_len_current":3,"time_since_last_flip":null,"npts_total":5,"env_z_season":-0.409428893533322,"stratum":"Mid","confidence_bucket":null},"0053000000000000241a":{"cluster_role_mapped":"Bare","best_soft_norm":0.667538978892326,"uncertain":false,"flipped_this_season":false,"streak_len_current":3,"time_since_last_flip":null,"npts_total":5,"env_z_season":0.23999217883211993,"stratum":"Mid","confidence_bucket":null},"0053000000000000241b":{"cluster_role_mapped":"Cover","best_soft_norm":0.0,"uncertain":true,"flipped_this_season":false,"streak_len_current":3,"time_since_last_flip":null,"npts_total":5,"env_z_season":3.0,"stratum":"Mid","confidence_bucket":null},"0053000000000000241c":{"cluster_role_mapped":"Bare","best_soft_norm":0.45193337055999044,"uncertain":false,"flipped_this_season":false,"streak_len_current":3,"time_since_last_flip":null,"npts_total":5,"env_z_season":-1.3240463543474832,"stratum":"Mid","confidence_bucket":null},"0053000000000000241d":{"cluster_role_mapped":"Cover","best_soft_norm":0.10999192279189811,"uncertain":true,"flipped_this_season":true,"streak_len_current":1,"time_since_last_flip":0,"npts_total":5,"env_z_season":2.1190377164101846,"stratum":"Mid","confidence_bucket":null},"0053000000000000241f":{"cluster_role_mapped":"Cover","best_soft_norm":0.041818770707157414,"uncertain":true,"flipped_this_season":false,"streak_len_current":2,"time_since_last_flip":1,"npts_total":5,"env_z_season":1.0844255611661442,"stratum":"Mid","confidence_bucket":null},"00530000000000002420":{"cluster_role_mapped":"Bare","best_soft_norm":0.9888681820955045,"uncertain":false,"flipped_this_season":false,"streak_len_current":3,"time_since_last_flip":null,"npts_total":5,"env_z_season":-0.36260359789292196,"stratum":"Mid","confidence_bucket":null},"00530000000000002424":{"cluster_role_mapped":"Bare","best_soft_norm":0.11053710507316827,"uncertain":true,"flipped_this_season":true,"streak_len_current":1,"time_since_last_flip":0,"npts_total":5,"env_z_season":0.5032227020444967,"stratum":"Mid","confidence_bucket":null},"0053000000000000242b":{"cluster_role_mapped":"Bare","best_soft_norm":0.9610122159568016,"uncertain":false,"flipped_this_season":false,"streak_len_current":3,"time_since_last_flip":null,"npts_total":5,"env_z_season":-0.07392234166586828,"stratum":"Mid","confidence_bucket":null},"0053000000000000242f":{"cluster_role_mapped":"Bare","best_soft_norm":1.0,"uncertain":false,"flipped_this_season":false,"streak_len_current":3,"time_since_last_flip":null,"npts_total":5,"env_z_season":-0.20035775938634925,"stratum":"Mid","confidence_bucket":null},"00530000000000002432":{"cluster_role_mapped":"Cover","best_soft_norm":0.6000345457370205,"uncertain":false,"flipped_this_season":false,"streak_len_current":3,"time_since_last_flip":null,"npts_total":5,"env_z_season":0.7189918145165545,"stratum":"Mid","confidence_bucket":null},"00530000000000002435":{"cluster_role_mapped":"Bare","best_soft_norm":0.629645895200687,"uncertain":false,"flipped_this_season":false,"streak_len_current":3,"time_since_last_flip":null,"npts_total":5,"env_z_season":0.25411579211628293,"stratum":"Mid","confidence_bucket":null},"0053000000000000243d":{"cluster_role_mapped":"Bare","best_soft_norm":0.9291479443582623,"uncertain":false,"flipped_this_season":false,"streak_len_current":3,"time_since_last_flip":null,"npts_total":5,"env_z_season":-0.391852975051449,"stratum":"Mid","confidence_bucket":null},"0053000000000000243f":{"cluster_role_mapped":"Cover","best_soft_norm":0.25590315242606293,"uncertain":false,"flipped_this_season":false,"streak_len_current":2,"time_since_last_flip":1,"npts_total":5,"env_z_season":0.22216195568626734,"stratum":"Mid","confidence_bucket":null},"00530000000000002440":{"cluster_role_mapped":"Cover","best_soft_norm":0.18265717664360218,"uncertain":false,"flipped_this_season":false,"streak_len_current":2,"time_since_last_flip":1,"npts_total":5,"env_z_season":0.05140741167718983,"stratum":"Mid","confidence_bucket":null},"00530000000000002442":{"cluster_role_mapped":"Bare","best_soft_norm":0.8101407179102106,"uncertain":false,"flipped_this_season":false,"streak_len_current":3,"time_since_last_flip":null,"npts_total":5,"env_z_season":-0.7268779599229854,"stratum":"Mid","confidence_bucket":null},"00530000000000002443":{"cluster_role_mapped":"Cover","best_soft_norm":0.0,"uncertain":true,"flipped_this_season":false,"streak_len_current":2,"time_since_last_flip":1,"npts_total":5,"env_z_season":-0.25125386680814343,"stratum":"Mid","confidence_bucket":null},"00530000000000002445":{"cluster_role_mapped":"Bare","best_soft_norm":0.6139461248254868,"uncertain":false,"flipped_this_season":false,"streak_len_current":3,"time_since_last_flip":null,"npts_total":5,"env_z_season":-1.0200716826237766,"stratum":"Mid","confidence_bucket":null},"00530000000000002446":{"cluster_role_mapped":"Bare","best_soft_norm":0.4711963970459093,"uncertain":false,"flipped_this_season":false,"streak_len_current":3,"time_since_last_flip":null,"npts_total":5,"env_z_season":-1.3550105684331515,"stratum":"Mid","confidence_bucket":null},"00530000000000002448":{"cluster_role_mapped":"Bare","best_soft_norm":0.48281404381592424,"uncertain":false,"flipped_this_season":false,"streak_len_current":3,"time_since_last_flip":null,"npts_total":5,"env_z_season":-1.3524802784383598,"stratum":"Mid","confidence_bucket":null},"00530000000000002449":{"cluster_role_mapped":"Cover","best_soft_norm":0.6069962801060069,"uncertain":false,"flipped_this_season":false,"streak_len_current":2,"time_since_last_flip":1,"npts_total":5,"env_z_season":0.7346714450157714,"stratum":"Mid","confidence_bucket":null},"0053000000000000244b":{"cluster_role_mapped":"Bare","best_soft_norm":0.47467107182438445,"uncertain":false,"flipped_this_season":false,"streak_len_current":3,"time_since_last_flip":null,"npts_total":5,"env_z_season":-1.3785435180905137,"stratum":"Mid","confidence_bucket":null},"0053000000000000244c":{"cluster_role_mapped":"Bare","best_soft_norm":0.0,"uncertain":true,"flipped_this_season":true,"streak_len_current":1,"time_since_last_flip":0,"npts_total":5,"env_z_season":0.8774922859933515,"stratum":"Mid","confidence_bucket":null},"0053000000000000244d":{"cluster_role_mapped":"Cover","best_soft_norm":0.0,"uncertain":true,"flipped_this_season":false,"streak_len_current":2,"time_since_last_flip":1,"npts_total":5,"env_z_season":-0.15138663178521858,"stratum":"Mid","confidence_bucket":null},"0053000000000000244e":{"cluster_role_mapped":"Bare","best_soft_norm":0.43210341079513215,"uncertain":false,"flipped_this_season":true,"streak_len_current":1,"time_since_last_flip":0,"npts_total":5,"env_z_season":0.3050551501069489,"stratum":"Mid","confidence_bucket":null},"00530000000000002453":{"cluster_role_mapped":"Bare","best_soft_norm":0.8462780721062162,"uncertain":false,"flipped_this_season":false,"streak_len_current":3,"time_since_last_flip":null,"npts_total":5,"env_z_season":-0.6805494428358337,"stratum":"Mid","confidence_bucket":null},"00530000000000002456":{"cluster_role_mapped":"Bare","best_soft_norm":0.6388769285349372,"uncertain":false,"flipped_this_season":false,"streak_len_current":3,"time_since_last_flip":null,"npts_total":5,"env_z_season":-0.958930881842673,"stratum":"Mid","confidence_bucket":null},"00530000000000002457":{"cluster_role_mapped":"Bare","best_soft_norm":0.1444546019135939,"uncertain":true,"flipped_this_season":false,"streak_len_current":3,"time_since_last_flip":null,"npts_total":5,"env_z_season":0.06720691344359384,"stratum":"Mid","confidence_bucket":null},"00530000000000002458":{"cluster_role_mapped":"Cover","best_soft_norm":0.4326748293657549,"uncertain":false,"flipped_this_season":true,"streak_len_current":1,"time_since_last_flip":0,"npts_total":5,"env_z_season":2.319505207487242,"stratum":"Mid","confidence_bucket":null},"0053000000000000245a":{"cluster_role_mapped":"Cover","best_soft_norm":0.3349345570748108,"uncertain":false,"flipped_this_season":false,"streak_len_current":2,"time_since_last_flip":1,"npts_total":5,"env_z_season":2.7325490838136064,"stratum":"Mid","confidence_bucket":null},"0053000000000000245c":{"cluster_role_mapped":"Bare","best_soft_norm":0.5221560910685997,"uncertain":false,"flipped_this_season":false,"streak_len_current":3,"time_since_last_flip":null,"npts_total":5,"env_z_season":-1.143792955761478,"stratum":"Mid","confidence_bucket":null},"0053000000000000245d":{"cluster_role_mapped":"Bare","best_soft_norm":0.40536594979869606,"uncertain":false,"flipped_this_season":false,"streak_len_current":3,"time_since_last_flip":null,"npts_total":5,"env_z_season":-1.5262906432686258,"stratum":"Mid","confidence_bucket":null},"0053000000000000245e":{"cluster_role_mapped":"Bare","best_soft_norm":0.8218104909022792,"uncertain":false,"flipped_this_season":false,"streak_len_current":3,"time_since_last_flip":null,"npts_total":5,"env_z_season":-0.6942912862138547,"stratum":"Mid","confidence_bucket":null},"00530000000000002460":{"cluster_role_mapped":"Bare","best_soft_norm":0.6665894385547761,"uncertain":false,"flipped_this_season":false,"streak_len_current":3,"time_since_last_flip":null,"npts_total":5,"env_z_season":-0.872553802363244,"stratum":"Mid","confidence_bucket":null},"00530000000000002461":{"cluster_role_mapped":"Cover","best_soft_norm":0.29039739811263454,"uncertain":false,"flipped_this_season":false,"streak_len_current":3,"time_since_last_flip":null,"npts_total":5,"env_z_season":3.0,"stratum":"Mid","confidence_bucket":null},"00530000000000002462":{"cluster_role_mapped":"Cover","best_soft_norm":0.3694392826323642,"uncertain":false,"flipped_this_season":true,"streak_len_current":1,"time_since_last_flip":0,"npts_total":5,"env_z_season":2.5757780786499263,"stratum":"Mid","confidence_bucket":null},"00530000000000002463":{"cluster_role_mapped":"Cover","best_soft_norm":0.3332122891361008,"uncertain":false,"flipped_this_season":false,"streak_len_current":2,"time_since_last_flip":1,"npts_total":5,"env_z_season":2.6445674839868105,"stratum":"Mid","confidence_bucket":null},"00530000000000002464":{"cluster_role_mapped":"Cover","best_soft_norm":0.31582943994652957,"uncertain":false,"flipped_this_season":false,"streak_len_current":2,"time_since_last_flip":1,"npts_total":5,"env_z_season":2.778577801675226,"stratum":"Mid","confidence_bucket":null},"00530000000000002465":{"cluster_role_mapped":"Bare","best_soft_norm":0.8335060843226855,"uncertain":false,"flipped_this_season":false,"streak_len_current":3,"time_since_last_flip":null,"npts_total":5,"env_z_season":-0.6967732150165731,"stratum":"Mid","confidence_bucket":null},"00530000000000002466":{"cluster_role_mapped":"Cover","best_soft_norm":0.0,"uncertain":true,"flipped_this_season":true,"streak_len_current":1,"time_since_last_flip":0,"npts_total":5,"env_z_season":1.0221914229447913,"stratum":"Mid","confidence_bucket":null},"0053000000000000246a":{"cluster_role_mapped":"Cover","best_soft_norm":0.2465658002256883,"uncertain":false,"flipped_this_season":true,"streak_len_current":1,"time_since_last_flip":0,"npts_total":5,"env_z_season":1.0342867983764896,"stratum":"Mid","confidence_bucket":null},"0053000000000000246c":{"cluster_role_mapped":"Bare","best_soft_norm":0.5367967450318621,"uncertain":false,"flipped_this_season":true,"streak_len_current":1,"time_since_last_flip":0,"npts_total":5,"env_z_season":-0.97512512702412,"stratum":"Mid","confidence_bucket":null},"00530000000000002474":{"cluster_role_mapped":"Bare","best_soft_norm":0.4900091265203704,"uncertain":false,"flipped_this_season":false,"streak_len_current":3,"time_since_last_flip":null,"npts_total":5,"env_z_season":-1.328014086919464,"stratum":"Mid","confidence_bucket":null},"00530000000000002477":{"cluster_role_mapped":"Bare","best_soft_norm":0.4601115907436121,"uncertain":false,"flipped_this_season":false,"streak_len_current":3,"time_since_last_flip":null,"npts_total":5,"env_z_season":-0.7149771600392865,"stratum":"Mid","confidence_bucket":null},"00530000000000002478":{"cluster_role_mapped":"Bare","best_soft_norm":0.6303709244485836,"uncertain":false,"flipped_this_season":false,"streak_len_current":3,"time_since_last_flip":null,"npts_total":5,"env_z_season":-0.9081175398185719,"stratum":"Mid","confidence_bucket":null},"00530000000000002479":{"cluster_role_mapped":"Bare","best_soft_norm":0.4430079178158496,"uncertain":false,"flipped_this_season":false,"streak_len_current":3,"time_since_last_flip":null,"npts_total":5,"env_z_season":-1.381967120746758,"stratum":"Mid","confidence_bucket":null},"0053000000000000247a":{"cluster_role_mapped":"Bare","best_soft_norm":0.5614984971700316,"uncertain":false,"flipped_this_season":false,"streak_len_current":3,"time_since_last_flip":null,"npts_total":5,"env_z_season":-1.1230283412866158,"stratum":"Mid","confidence_bucket":null},"0053000000000000247c":{"cluster_role_mapped":"Bare","best_soft_norm":0.6289586110862275,"uncertain":false,"flipped_this_season":false,"streak_len_current":3,"time_since_last_flip":null,"npts_total":5,"env_z_season":-0.8996088523138663,"stratum":"Mid","confidence_bucket":null},"00530000000000002480":{"cluster_role_mapped":"Bare","best_soft_norm":0.7993384570730145,"uncertain":false,"flipped_this_season":false,"streak_len_current":3,"time_since_last_flip":null,"npts_total":5,"env_z_season":-0.7278688845316222,"stratum":"Mid","confidence_bucket":null},"00530000000000002481":{"cluster_role_mapped":"Cover","best_soft_norm":0.31216645063000775,"uncertain":false,"flipped_this_season":true,"streak_len_current":1,"time_since_last_flip":0,"npts_total":5,"env_z_season":0.550403359359684,"stratum":"Mid","confidence_bucket":null},"00530000000000002483":{"cluster_role_mapped":"Cover","best_soft_norm":0.3700068192752022,"uncertain":false,"flipped_this_season":false,"streak_len_current":2,"time_since_last_flip":1,"npts_total":5,"env_z_season":0.43975753797314154,"stratum":"Mid","confidence_bucket":null},"00530000000000002484":{"cluster_role_mapped":"Bare","best_soft_norm":0.46459023766099955,"uncertain":false,"flipped_this_season":false,"streak_len_current":3,"time_since_last_flip":null,"npts_total":5,"env_z_season":-0.47783865392744,"stratum":"Mid","confidence_bucket":null},"005300000000000024b4":{"cluster_role_mapped":"Bare","best_soft_norm":0.6205140408310209,"uncertain":false,"flipped_this_season":false,"streak_len_current":3,"time_since_last_flip":null,"npts_total":5,"env_z_season":0.22158332823927837,"stratum":"Mid","confidence_bucket":null},"005300000000000024b9":{"cluster_role_mapped":"Cover","best_soft_norm":0.06670343294554693,"uncertain":true,"flipped_this_season":false,"streak_len_current":2,"time_since_last_flip":1,"npts_total":5,"env_z_season":-0.27856598660601284,"stratum":"Mid","confidence_bucket":null},"005300000000000024ba":{"cluster_role_mapped":"Cover","best_soft_norm":0.0,"uncertain":true,"flipped_this_season":false,"streak_len_current":2,"time_since_last_flip":1,"npts_total":5,"env_z_season":-0.7052317137974949,"stratum":"Mid","confidence_bucket":null},"005300000000000024bc":{"cluster_role_mapped":"Bare","best_soft_norm":0.7450493207831546,"uncertain":false,"flipped_this_season":false,"streak_len_current":3,"time_since_last_flip":null,"npts_total":5,"env_z_season":-0.01451563633477909,"stratum":"Mid","confidence_bucket":null},"005300000000000024bd":{"cluster_role_mapped":"Bare","best_soft_norm":0.3298654886090484,"uncertain":false,"flipped_this_season":false,"streak_len_current":3,"time_since_last_flip":null,"npts_total":5,"env_z_season":-1.0477237252402416,"stratum":"Mid","confidence_bucket":null},"005300000000000024bf":{"cluster_role_mapped":"Bare","best_soft_norm":0.5188231199995377,"uncertain":false,"flipped_this_season":false,"streak_len_current":3,"time_since_last_flip":null,"npts_total":5,"env_z_season":-0.8215364498542441,"stratum":"Mid","confidence_bucket":null},"005300000000000024c1":{"cluster_role_mapped":"Cover","best_soft_norm":0.0,"uncertain":true,"flipped_this_season":false,"streak_len_current":2,"time_since_last_flip":1,"npts_total":5,"env_z_season":-0.6917870251676013,"stratum":"Mid","confidence_bucket":null},"005300000000000024c6":{"cluster_role_mapped":"Bare","best_soft_norm":0.9608416718653159,"uncertain":false,"flipped_this_season":false,"streak_len_current":2,"time_since_last_flip":1,"npts_total":5,"env_z_season":-0.24951863020484627,"stratum":"Mid","confidence_bucket":null},"005300000000000024ca":{"cluster_role_mapped":"Bare","best_soft_norm":0.06880531344221116,"uncertain":true,"flipped_this_season":false,"streak_len_current":2,"time_since_last_flip":1,"npts_total":5,"env_z_season":-0.0027397253243632547,"stratum":"Mid","confidence_bucket":null},"005300000000000024d2":{"cluster_role_mapped":"Bare","best_soft_norm":0.9672152305497085,"uncertain":false,"flipped_this_season":false,"streak_len_current":3,"time_since_last_flip":null,"npts_total":5,"env_z_season":-0.09703011483947754,"stratum":"Mid","confidence_bucket":null},"005300000000000024d4":{"cluster_role_mapped":"Bare","best_soft_norm":0.3538105461119642,"uncertain":false,"flipped_this_season":false,"streak_len_current":3,"time_since_last_flip":null,"npts_total":5,"env_z_season":-1.3563788301476782,"stratum":"Mid","confidence_bucket":null},"005300000000000024e4":{"cluster_role_mapped":"Cover","best_soft_norm":0.0898956139918149,"uncertain":true,"flipped_this_season":true,"streak_len_current":1,"time_since_last_flip":0,"npts_total":5,"env_z_season":-0.189205897583324,"stratum":"Mid","confidence_bucket":null},"00530000000000002bb2":{"cluster_role_mapped":"Bare","best_soft_norm":1.0,"uncertain":false,"flipped_this_season":false,"streak_len_current":3,"time_since_last_flip":null,"npts_total":5,"env_z_season":-0.36361239555843633,"stratum":"Mid","confidence_bucket":null},"00530000000000002bb3":{"cluster_role_mapped":"Bare","best_soft_norm":1.0,"uncertain":false,"flipped_this_season":false,"streak_len_current":3,"time_since_last_flip":null,"npts_total":5,"env_z_season":-0.19032954238064875,"stratum":"Mid","confidence_bucket":null},"00530000000000002bb4":{"cluster_role_mapped":"Bare","best_soft_norm":0.7507785315775224,"uncertain":false,"flipped_this_season":false,"streak_len_current":3,"time_since_last_flip":null,"npts_total":5,"env_z_season":0.09416887478597803,"stratum":"Mid","confidence_bucket":null},"00530000000000003790":{"cluster_role_mapped":"Bare","best_soft_norm":0.6926481937478107,"uncertain":false,"flipped_this_season":true,"streak_len_current":1,"time_since_last_flip":0,"npts_total":5,"env_z_season":-0.32938273343938457,"stratum":"Mid","confidence_bucket":null},"00530000000000003796":{"cluster_role_mapped":"Bare","best_soft_norm":0.8691339924131748,"uncertain":false,"flipped_this_season":false,"streak_len_current":2,"time_since_last_flip":1,"npts_total":5,"env_z_season":0.011174876693685406,"stratum":"Mid","confidence_bucket":null},"00530000000000003797":{"cluster_role_mapped":"Bare","best_soft_norm":0.6701140662713955,"uncertain":false,"flipped_this_season":false,"streak_len_current":3,"time_since_last_flip":null,"npts_total":5,"env_z_season":-0.8280175815489926,"stratum":"Mid","confidence_bucket":null},"00530000000000003798":{"cluster_role_mapped":"Cover","best_soft_norm":0.14578262454972504,"uncertain":true,"flipped_this_season":false,"streak_len_current":3,"time_since_last_flip":null,"npts_total":5,"env_z_season":0.1259053009065083,"stratum":"Mid","confidence_bucket":null},"00530000000000004359":{"cluster_role_mapped":"Bare","best_soft_norm":0.8945668687540739,"uncertain":false,"flipped_this_season":false,"streak_len_current":2,"time_since_last_flip":1,"npts_total":5,"env_z_season":-0.00795808348598931,"stratum":"Mid","confidence_bucket":null},"0053000000000000499b":{"cluster_role_mapped":"Bare","best_soft_norm":0.41599870130498345,"uncertain":false,"flipped_this_season":false,"streak_len_current":3,"time_since_last_flip":null,"npts_total":5,"env_z_season":-1.4353373743959772,"stratum":"Mid","confidence_bucket":null},"00530000000000004bc1":{"cluster_role_mapped":"Bare","best_soft_norm":0.3031286221915335,"uncertain":false,"flipped_this_season":false,"streak_len_current":3,"time_since_last_flip":null,"npts_total":5,"env_z_season":-0.4426340484181022,"stratum":"Mid","confidence_bucket":null},"00530000000000004bc7":{"cluster_role_mapped":"Cover","best_soft_norm":0.02235330204310232,"uncertain":true,"flipped_this_season":false,"streak_len_current":2,"time_since_last_flip":1,"npts_total":5,"env_z_season":0.9848825757521258,"stratum":"Mid","confidence_bucket":null},"00530000000000004c31":{"cluster_role_mapped":"Cover","best_soft_norm":0.6464802376484023,"uncertain":false,"flipped_this_season":true,"streak_len_current":1,"time_since_last_flip":0,"npts_total":5,"env_z_season":0.9567862321903351,"stratum":"Mid","confidence_bucket":null},"00530000000000004c32":{"cluster_role_mapped":"Bare","best_soft_norm":1.0,"uncertain":false,"flipped_this_season":false,"streak_len_current":3,"time_since_last_flip":null,"npts_total":5,"env_z_season":-0.07556935051707311,"stratum":"Mid","confidence_bucket":null},"00530000000000004c35":{"cluster_role_mapped":"Cover","best_soft_norm":0.8093450802735314,"uncertain":false,"flipped_this_season":false,"streak_len_current":3,"time_since_last_flip":null,"npts_total":5,"env_z_season":0.7621233719596039,"stratum":"Mid","confidence_bucket":null},"00530000000000004c3c":{"cluster_role_mapped":"Bare","best_soft_norm":0.014934811863617196,"uncertain":true,"flipped_this_season":false,"streak_len_current":2,"time_since_last_flip":1,"npts_total":5,"env_z_season":0.8463606284571374,"stratum":"Mid","confidence_bucket":null},"00530000000000004c3d":{"cluster_role_mapped":"Bare","best_soft_norm":1.0,"uncertain":false,"flipped_this_season":false,"streak_len_current":2,"time_since_last_flip":1,"npts_total":5,"env_z_season":-0.44349175447127775,"stratum":"Mid","confidence_bucket":null},"00530000000000004c47":{"cluster_role_mapped":"Cover","best_soft_norm":0.2668456310091141,"uncertain":false,"flipped_this_season":true,"streak_len_current":1,"time_since_last_flip":0,"npts_total":5,"env_z_season":2.208943302817104,"stratum":"Mid","confidence_bucket":null},"00530000000000004c49":{"cluster_role_mapped":"Bare","best_soft_norm":0.9001287019873897,"uncertain":false,"flipped_this_season":false,"streak_len_current":3,"time_since_last_flip":null,"npts_total":5,"env_z_season":-0.3626147971160028,"stratum":"Mid","confidence_bucket":null},"00530000000000004c4a":{"cluster_role_mapped":"Bare","best_soft_norm":0.2672824578342836,"uncertain":false,"flipped_this_season":false,"streak_len_current":3,"time_since_last_flip":null,"npts_total":5,"env_z_season":-0.791208882129499,"stratum":"Mid","confidence_bucket":null},"00530000000000004c4d":{"cluster_role_mapped":"Cover","best_soft_norm":0.22173449087399622,"uncertain":false,"flipped_this_season":true,"streak_len_current":1,"time_since_last_flip":0,"npts_total":5,"env_z_season":0.914426350163768,"stratum":"Mid","confidence_bucket":null},"00530000000000004c51":{"cluster_role_mapped":"Cover","best_soft_norm":0.06399962515815129,"uncertain":true,"flipped_this_season":false,"streak_len_current":3,"time_since_last_flip":null,"npts_total":5,"env_z_season":3.0,"stratum":"Mid","confidence_bucket":null},"00530000000000004c53":{"cluster_role_mapped":"Cover","best_soft_norm":0.0,"uncertain":true,"flipped_this_season":false,"streak_len_current":3,"time_since_last_flip":null,"npts_total":5,"env_z_season":3.0,"stratum":"Mid","confidence_bucket":null},"00530000000000004c55":{"cluster_role_mapped":"Bare","best_soft_norm":0.44412913243355484,"uncertain":false,"flipped_this_season":false,"streak_len_current":3,"time_since_last_flip":null,"npts_total":5,"env_z_season":0.37627247597398605,"stratum":"Mid","confidence_bucket":null},"00530000000000004c56":{"cluster_role_mapped":"Bare","best_soft_norm":0.1587695403444128,"uncertain":false,"flipped_this_season":true,"streak_len_current":1,"time_since_last_flip":0,"npts_total":5,"env_z_season":0.03381307478715184,"stratum":"Mid","confidence_bucket":null},"00530000000000004c59":{"cluster_role_mapped":"Bare","best_soft_norm":0.6318440386025619,"uncertain":false,"flipped_this_season":false,"streak_len_current":3,"time_since_last_flip":null,"npts_total":5,"env_z_season":-0.8369070118704602,"stratum":"Mid","confidence_bucket":null},"00530000000000004c5a":{"cluster_role_mapped":"Bare","best_soft_norm":0.4980882848743114,"uncertain":false,"flipped_this_season":false,"streak_len_current":3,"time_since_last_flip":null,"npts_total":5,"env_z_season":-0.5148771855562162,"stratum":"Mid","confidence_bucket":null},"00530000000000004c5d":{"cluster_role_mapped":"Bare","best_soft_norm":0.6809568301660558,"uncertain":false,"flipped_this_season":true,"streak_len_current":1,"time_since_last_flip":0,"npts_total":5,"env_z_season":-0.8077985694855315,"stratum":"Mid","confidence_bucket":null},"00530000000000004c74":{"cluster_role_mapped":"Bare","best_soft_norm":0.3189821213619155,"uncertain":false,"flipped_this_season":true,"streak_len_current":1,"time_since_last_flip":0,"npts_total":5,"env_z_season":-0.012540216369648985,"stratum":"Mid","confidence_bucket":null},"00530000000000004c77":{"cluster_role_mapped":"Bare","best_soft_norm":1.0,"uncertain":false,"flipped_this_season":false,"streak_len_current":3,"time_since_last_flip":null,"npts_total":5,"env_z_season":-0.3341554622062482,"stratum":"Mid","confidence_bucket":null},"00530000000000004c7b":{"cluster_role_mapped":"Bare","best_soft_norm":0.0,"uncertain":true,"flipped_this_season":false,"streak_len_current":2,"time_since_last_flip":1,"npts_total":5,"env_z_season":0.8200515002818342,"stratum":"Mid","confidence_bucket":null},"00530000000000004c86":{"cluster_role_mapped":"Cover","best_soft_norm":0.3555274537150629,"uncertain":false,"flipped_this_season":false,"streak_len_current":3,"time_since_last_flip":null,"npts_total":5,"env_z_season":2.355060811222123,"stratum":"Mid","confidence_bucket":null},"00530000000000004c88":{"cluster_role_mapped":"Bare","best_soft_norm":0.2040458582034418,"uncertain":false,"flipped_this_season":true,"streak_len_current":1,"time_since_last_flip":0,"npts_total":5,"env_z_season":-0.30537787323188287,"stratum":"Mid","confidence_bucket":null},"00530000000000004c8c":{"cluster_role_mapped":"Cover","best_soft_norm":0.8951560138201249,"uncertain":false,"flipped_this_season":false,"streak_len_current":3,"time_since_last_flip":null,"npts_total":5,"env_z_season":1.4328842880659733,"stratum":"Mid","confidence_bucket":null},"00530000000000004c8f":{"cluster_role_mapped":"Bare","best_soft_norm":0.2255189661386267,"uncertain":false,"flipped_this_season":false,"streak_len_current":2,"time_since_last_flip":1,"npts_total":5,"env_z_season":0.05649934374910285,"stratum":"Mid","confidence_bucket":null},"00530000000000004c92":{"cluster_role_mapped":"Cover","best_soft_norm":0.023162402639308743,"uncertain":true,"flipped_this_season":true,"streak_len_current":1,"time_since_last_flip":0,"npts_total":5,"env_z_season":3.0,"stratum":"Mid","confidence_bucket":null},"00530000000000004c98":{"cluster_role_mapped":"Bare","best_soft_norm":0.2923844031875502,"uncertain":false,"flipped_this_season":true,"streak_len_current":1,"time_since_last_flip":0,"npts_total":5,"env_z_season":0.40052748224190776,"stratum":"Mid","confidence_bucket":null},"00530000000000004ca2":{"cluster_role_mapped":"Bare","best_soft_norm":0.7045386703924436,"uncertain":false,"flipped_this_season":false,"streak_len_current":3,"time_since_last_flip":null,"npts_total":5,"env_z_season":0.05872787078637529,"stratum":"Mid","confidence_bucket":null},"00530000000000004cb1":{"cluster_role_mapped":"Cover","best_soft_norm":0.2016690274026817,"uncertain":false,"flipped_this_season":true,"streak_len_current":1,"time_since_last_flip":0,"npts_total":5,"env_z_season":1.709840411786357,"stratum":"Mid","confidence_bucket":null},"00530000000000004cb4":{"cluster_role_mapped":"Bare","best_soft_norm":0.006131626232796812,"uncertain":true,"flipped_this_season":false,"streak_len_current":3,"time_since_last_flip":null,"npts_total":5,"env_z_season":0.9908040631465951,"stratum":"Mid","confidence_bucket":null},"00530000000000004cb7":{"cluster_role_mapped":"Bare","best_soft_norm":1.0,"uncertain":false,"flipped_this_season":false,"streak_len_current":3,"time_since_last_flip":null,"npts_total":5,"env_z_season":-0.25104220315005515,"stratum":"Mid","confidence_bucket":null},"00530000000000004cb9":{"cluster_role_mapped":"Bare","best_soft_norm":1.0,"uncertain":false,"flipped_this_season":false,"streak_len_current":3,"time_since_last_flip":null,"npts_total":5,"env_z_season":-0.34352972592393394,"stratum":"Mid","confidence_bucket":null},"00530000000000004cc9":{"cluster_role_mapped":"Cover","best_soft_norm":0.0,"uncertain":true,"flipped_this_season":false,"streak_len_current":3,"time_since_last_flip":null,"npts_total":5,"env_z_season":1.0611091223604696,"stratum":"Mid","confidence_bucket":null},"00530000000000004cda":{"cluster_role_mapped":"Bare","best_soft_norm":0.9107336646360771,"uncertain":false,"flipped_this_season":false,"streak_len_current":3,"time_since_last_flip":null,"npts_total":5,"env_z_season":0.02445469257326263,"stratum":"Mid","confidence_bucket":null},"00530000000000004ce7":{"cluster_role_mapped":"Bare","best_soft_norm":1.0,"uncertain":false,"flipped_this_season":false,"streak_len_current":3,"time_since_last_flip":null,"npts_total":5,"env_z_season":-0.331692341692712,"stratum":"Mid","confidence_bucket":null},"00530000000000004cf6":{"cluster_role_mapped":"Bare","best_soft_norm":0.2096876618652335,"uncertain":false,"flipped_this_season":false,"streak_len_current":3,"time_since_last_flip":null,"npts_total":5,"env_z_season":0.5752836440151103,"stratum":"Mid","confidence_bucket":null},"00530000000000004cfc":{"cluster_role_mapped":"Cover","best_soft_norm":0.15611426585412455,"uncertain":false,"flipped_this_season":true,"streak_len_current":1,"time_since_last_flip":0,"npts_total":5,"env_z_season":1.2437484163689234,"stratum":"Mid","confidence_bucket":null},"00530000000000004cfd":{"cluster_role_mapped":"Bare","best_soft_norm":0.02907166135873271,"uncertain":true,"flipped_this_season":true,"streak_len_current":1,"time_since_last_flip":0,"npts_total":5,"env_z_season":0.6646951931586688,"stratum":"Mid","confidence_bucket":null},"00530000000000004d00":{"cluster_role_mapped":"Bare","best_soft_norm":0.011435119847492606,"uncertain":true,"flipped_this_season":false,"streak_len_current":2,"time_since_last_flip":1,"npts_total":5,"env_z_season":0.8977366261178795,"stratum":"Mid","confidence_bucket":null},"00530000000000004ec9":{"cluster_role_mapped":"Bare","best_soft_norm":0.5180774164972022,"uncertain":false,"flipped_this_season":false,"streak_len_current":3,"time_since_last_flip":null,"npts_total":5,"env_z_season":0.22635952884030633,"stratum":"Mid","confidence_bucket":null},"00530000000000004eca":{"cluster_role_mapped":"Bare","best_soft_norm":0.99302601692638,"uncertain":false,"flipped_this_season":false,"streak_len_current":3,"time_since_last_flip":null,"npts_total":5,"env_z_season":-0.1992761107160889,"stratum":"Mid","confidence_bucket":null},"00530000000000004ecb":{"cluster_role_mapped":"Bare","best_soft_norm":0.5414099239937894,"uncertain":false,"flipped_this_season":false,"streak_len_current":3,"time_since_last_flip":null,"npts_total":5,"env_z_season":-0.23400391551983352,"stratum":"Mid","confidence_bucket":null},"00530000000000004f20":{"cluster_role_mapped":"Cover","best_soft_norm":0.15511170311946768,"uncertain":false,"flipped_this_season":false,"streak_len_current":3,"time_since_last_flip":null,"npts_total":5,"env_z_season":2.779166530103536,"stratum":"Mid","confidence_bucket":null},"00530000000000004f34":{"cluster_role_mapped":"Bare","best_soft_norm":0.7533722535166909,"uncertain":false,"flipped_this_season":false,"streak_len_current":3,"time_since_last_flip":null,"npts_total":5,"env_z_season":-0.7435763396212733,"stratum":"Mid","confidence_bucket":null},"00530000000000004f8a":{"cluster_role_mapped":"Bare","best_soft_norm":1.0,"uncertain":false,"flipped_this_season":true,"streak_len_current":1,"time_since_last_flip":0,"npts_total":5,"env_z_season":-0.29421694186929825,"stratum":"Mid","confidence_bucket":null},"00530000000000004f8c":{"cluster_role_mapped":"Bare","best_soft_norm":0.8591167751461901,"uncertain":false,"flipped_this_season":false,"streak_len_current":3,"time_since_last_flip":null,"npts_total":5,"env_z_season":0.037162728721208196,"stratum":"Mid","confidence_bucket":null},"00530000000000004f8d":{"cluster_role_mapped":"Cover","best_soft_norm":0.0,"uncertain":true,"flipped_this_season":true,"streak_len_current":1,"time_since_last_flip":0,"npts_total":5,"env_z_season":0.93296290969654,"stratum":"Mid","confidence_bucket":null},"00530000000000004f8f":{"cluster_role_mapped":"Cover","best_soft_norm":0.37608194515612114,"uncertain":false,"flipped_this_season":false,"streak_len_current":3,"time_since_last_flip":null,"npts_total":5,"env_z_season":0.6849277470494197,"stratum":"Mid","confidence_bucket":null},"00530000000000004f90":{"cluster_role_mapped":"Cover","best_soft_norm":0.3797497754200253,"uncertain":false,"flipped_this_season":true,"streak_len_current":1,"time_since_last_flip":0,"npts_total":5,"env_z_season":1.2680172151378932,"stratum":"Mid","confidence_bucket":null},"00530000000000004f92":{"cluster_role_mapped":"Cover","best_soft_norm":0.0,"uncertain":true,"flipped_this_season":true,"streak_len_current":1,"time_since_last_flip":0,"npts_total":5,"env_z_season":0.8373865241608903,"stratum":"Mid","confidence_bucket":null},"00530000000000004f93":{"cluster_role_mapped":"Cover","best_soft_norm":0.13393681163528653,"uncertain":true,"flipped_this_season":true,"streak_len_current":1,"time_since_last_flip":0,"npts_total":5,"env_z_season":1.1868337159384068,"stratum":"Mid","confidence_bucket":null},"00530000000000004f94":{"cluster_role_mapped":"Bare","best_soft_norm":0.6080455466762507,"uncertain":false,"flipped_this_season":false,"streak_len_current":3,"time_since_last_flip":null,"npts_total":5,"env_z_season":0.25661701005470505,"stratum":"Mid","confidence_bucket":null},"00530000000000004f95":{"cluster_role_mapped":"Bare","best_soft_norm":0.2691174267972686,"uncertain":false,"flipped_this_season":true,"streak_len_current":1,"time_since_last_flip":0,"npts_total":5,"env_z_season":0.4168859655788181,"stratum":"Mid","confidence_bucket":null},"00530000000000004f98":{"cluster_role_mapped":"Bare","best_soft_norm":0.37892236014574315,"uncertain":false,"flipped_this_season":false,"streak_len_current":2,"time_since_last_flip":1,"npts_total":5,"env_z_season":-1.5978360130492975,"stratum":"Mid","confidence_bucket":null},"00530000000000004f99":{"cluster_role_mapped":"Bare","best_soft_norm":0.2270015915324776,"uncertain":false,"flipped_this_season":true,"streak_len_current":1,"time_since_last_flip":0,"npts_total":5,"env_z_season":-2.0577192871245638,"stratum":"Mid","confidence_bucket":null},"00530000000000004f9a":{"cluster_role_mapped":"Bare","best_soft_norm":0.0493611527781186,"uncertain":true,"flipped_this_season":true,"streak_len_current":1,"time_since_last_flip":0,"npts_total":5,"env_z_season":-0.003943786214787968,"stratum":"Mid","confidence_bucket":null},"00530000000000004f9b":{"cluster_role_mapped":"Bare","best_soft_norm":1.0,"uncertain":false,"flipped_this_season":false,"streak_len_current":3,"time_since_last_flip":null,"npts_total":5,"env_z_season":-0.20431457259708571,"stratum":"Mid","confidence_bucket":null},"00530000000000004f9c":{"cluster_role_mapped":"Bare","best_soft_norm":1.0,"uncertain":false,"flipped_this_season":false,"streak_len_current":3,"time_since_last_flip":null,"npts_total":5,"env_z_season":-0.275395008384665,"stratum":"Mid","confidence_bucket":null},"00530000000000004f9d":{"cluster_role_mapped":"Cover","best_soft_norm":0.5013371161649836,"uncertain":false,"flipped_this_season":false,"streak_len_current":2,"time_since_last_flip":1,"npts_total":5,"env_z_season":0.5344688531340382,"stratum":"Mid","confidence_bucket":null},"00530000000000004fa0":{"cluster_role_mapped":"Bare","best_soft_norm":0.9980876616666787,"uncertain":false,"flipped_this_season":false,"streak_len_current":3,"time_since_last_flip":null,"npts_total":5,"env_z_season":-0.09865866772463482,"stratum":"Mid","confidence_bucket":null},"00530000000000004fa1":{"cluster_role_mapped":"Cover","best_soft_norm":0.2656615772024634,"uncertain":false,"flipped_this_season":false,"streak_len_current":2,"time_since_last_flip":1,"npts_total":5,"env_z_season":2.2103664107693386,"stratum":"Mid","confidence_bucket":null},"00530000000000004fa3":{"cluster_role_mapped":"Bare","best_soft_norm":0.5810273882158976,"uncertain":false,"flipped_this_season":false,"streak_len_current":3,"time_since_last_flip":null,"npts_total":5,"env_z_season":0.3078297288748929,"stratum":"Mid","confidence_bucket":null},"00530000000000004fa4":{"cluster_role_mapped":"Cover","best_soft_norm":0.5485318809744874,"uncertain":false,"flipped_this_season":false,"streak_len_current":3,"time_since_last_flip":null,"npts_total":5,"env_z_season":1.1883682607195252,"stratum":"Mid","confidence_bucket":null},"00530000000000004fa5":{"cluster_role_mapped":"Bare","best_soft_norm":0.8841809255702742,"uncertain":false,"flipped_this_season":false,"streak_len_current":3,"time_since_last_flip":null,"npts_total":5,"env_z_season":-0.06448508472432171,"stratum":"Mid","confidence_bucket":null},"00530000000000004fa7":{"cluster_role_mapped":"Bare","best_soft_norm":0.18609919287053997,"uncertain":false,"flipped_this_season":false,"streak_len_current":3,"time_since_last_flip":null,"npts_total":5,"env_z_season":-0.5618421531266886,"stratum":"Mid","confidence_bucket":null},"00530000000000004fa8":{"cluster_role_mapped":"Bare","best_soft_norm":0.6814574137575766,"uncertain":false,"flipped_this_season":false,"streak_len_current":3,"time_since_last_flip":null,"npts_total":5,"env_z_season":-0.5230225921779661,"stratum":"Mid","confidence_bucket":null},"00530000000000004fa9":{"cluster_role_mapped":"Cover","best_soft_norm":0.60014970186546,"uncertain":false,"flipped_this_season":true,"streak_len_current":1,"time_since_last_flip":0,"npts_total":5,"env_z_season":0.6454096317505842,"stratum":"Mid","confidence_bucket":null},"00530000000000004faa":{"cluster_role_mapped":"Bare","best_soft_norm":0.9310046564995438,"uncertain":false,"flipped_this_season":false,"streak_len_current":3,"time_since_last_flip":null,"npts_total":5,"env_z_season":-0.21948619846134398,"stratum":"Mid","confidence_bucket":null},"00530000000000004fab":{"cluster_role_mapped":"Bare","best_soft_norm":0.6700802466510112,"uncertain":false,"flipped_this_season":false,"streak_len_current":3,"time_since_last_flip":null,"npts_total":5,"env_z_season":-0.7948806525007323,"stratum":"Mid","confidence_bucket":null},"00530000000000004fac":{"cluster_role_mapped":"Bare","best_soft_norm":0.9668984255272283,"uncertain":false,"flipped_this_season":false,"streak_len_current":3,"time_since_last_flip":null,"npts_total":5,"env_z_season":-0.06793791464604008,"stratum":"Mid","confidence_bucket":null},"00530000000000004fad":{"cluster_role_mapped":"Bare","best_soft_norm":1.0,"uncertain":false,"flipped_this_season":false,"streak_len_current":3,"time_since_last_flip":null,"npts_total":5,"env_z_season":-0.11827050246334322,"stratum":"Mid","confidence_bucket":null},"00530000000000004faf":{"cluster_role_mapped":"Bare","best_soft_norm":1.0,"uncertain":false,"flipped_this_season":false,"streak_len_current":3,"time_since_last_flip":null,"npts_total":5,"env_z_season":-0.39761559623916304,"stratum":"Mid","confidence_bucket":null},"00530000000000004fb0":{"cluster_role_mapped":"Bare","best_soft_norm":0.13557437933378993,"uncertain":true,"flipped_this_season":false,"streak_len_current":3,"time_since_last_flip":null,"npts_total":5,"env_z_season":0.8323922582299019,"stratum":"Mid","confidence_bucket":null},"00530000000000004fb1":{"cluster_role_mapped":"Bare","best_soft_norm":1.0,"uncertain":false,"flipped_this_season":false,"streak_len_current":3,"time_since_last_flip":null,"npts_total":5,"env_z_season":-0.05076175162099969,"stratum":"Mid","confidence_bucket":null},"00530000000000004fb3":{"cluster_role_mapped":"Cover","best_soft_norm":0.0,"uncertain":true,"flipped_this_season":true,"streak_len_current":1,"time_since_last_flip":0,"npts_total":5,"env_z_season":-0.3321760111054535,"stratum":"Mid","confidence_bucket":null},"00530000000000004fb6":{"cluster_role_mapped":"Cover","best_soft_norm":0.09585390932696619,"uncertain":true,"flipped_this_season":false,"streak_len_current":2,"time_since_last_flip":1,"npts_total":5,"env_z_season":1.188390335056199,"stratum":"Mid","confidence_bucket":null},"00530000000000004fb7":{"cluster_role_mapped":"Bare","best_soft_norm":0.36112482673086455,"uncertain":false,"flipped_this_season":false,"streak_len_current":3,"time_since_last_flip":null,"npts_total":5,"env_z_season":0.35303195123563946,"stratum":"Mid","confidence_bucket":null},"00530000000000004fba":{"cluster_role_mapped":"Bare","best_soft_norm":0.9161697940816099,"uncertain":false,"flipped_this_season":false,"streak_len_current":3,"time_since_last_flip":null,"npts_total":5,"env_z_season":-0.488629124903918,"stratum":"Mid","confidence_bucket":null},"00530000000000004fbb":{"cluster_role_mapped":"Bare","best_soft_norm":0.983453467281636,"uncertain":false,"flipped_this_season":true,"streak_len_current":1,"time_since_last_flip":0,"npts_total":5,"env_z_season":-0.40183505050584184,"stratum":"Mid","confidence_bucket":null},"00530000000000004fbd":{"cluster_role_mapped":"Bare","best_soft_norm":0.0,"uncertain":true,"flipped_this_season":false,"streak_len_current":3,"time_since_last_flip":null,"npts_total":5,"env_z_season":0.14802968887732065,"stratum":"Mid","confidence_bucket":null},"00530000000000004fc0":{"cluster_role_mapped":"Bare","best_soft_norm":1.0,"uncertain":false,"flipped_this_season":false,"streak_len_current":3,"time_since_last_flip":null,"npts_total":5,"env_z_season":-0.31672470931351376,"stratum":"Mid","confidence_bucket":null},"00530000000000004fc2":{"cluster_role_mapped":"Bare","best_soft_norm":1.0,"uncertain":false,"flipped_this_season":false,"streak_len_current":3,"time_since_last_flip":null,"npts_total":5,"env_z_season":-0.16133669854927873,"stratum":"Mid","confidence_bucket":null},"00530000000000004fc3":{"cluster_role_mapped":"Cover","best_soft_norm":0.38989955100010054,"uncertain":false,"flipped_this_season":false,"streak_len_current":2,"time_since_last_flip":1,"npts_total":5,"env_z_season":1.2246400843225194,"stratum":"Mid","confidence_bucket":null},"00530000000000004fc4":{"cluster_role_mapped":"Bare","best_soft_norm":0.0,"uncertain":true,"flipped_this_season":false,"streak_len_current":3,"time_since_last_flip":null,"npts_total":5,"env_z_season":0.534671671873165,"stratum":"Mid","confidence_bucket":null},"00530000000000004fc5":{"cluster_role_mapped":"Bare","best_soft_norm":0.7105855301776403,"uncertain":false,"flipped_this_season":false,"streak_len_current":3,"time_since_last_flip":null,"npts_total":5,"env_z_season":-0.7521072410316928,"stratum":"Mid","confidence_bucket":null},"00530000000000004fc6":{"cluster_role_mapped":"Bare","best_soft_norm":0.8340537280660386,"uncertain":false,"flipped_this_season":false,"streak_len_current":3,"time_since_last_flip":null,"npts_total":5,"env_z_season":-0.5776501076312773,"stratum":"Mid","confidence_bucket":null},"00530000000000004fc8":{"cluster_role_mapped":"Bare","best_soft_norm":0.10388906865643698,"uncertain":true,"flipped_this_season":false,"streak_len_current":3,"time_since_last_flip":null,"npts_total":5,"env_z_season":-1.6445698601864545,"stratum":"Mid","confidence_bucket":null},"00530000000000004fca":{"cluster_role_mapped":"Bare","best_soft_norm":0.9606838131700617,"uncertain":false,"flipped_this_season":false,"streak_len_current":3,"time_since_last_flip":null,"npts_total":5,"env_z_season":-0.43192857883746144,"stratum":"Mid","confidence_bucket":null},"00530000000000004fcc":{"cluster_role_mapped":"Bare","best_soft_norm":0.16615916539449677,"uncertain":false,"flipped_this_season":false,"streak_len_current":3,"time_since_last_flip":null,"npts_total":5,"env_z_season":-0.148617561518207,"stratum":"Mid","confidence_bucket":null},"00530000000000004fcd":{"cluster_role_mapped":"Bare","best_soft_norm":0.0,"uncertain":true,"flipped_this_season":false,"streak_len_current":3,"time_since_last_flip":null,"npts_total":5,"env_z_season":0.9652737376382426,"stratum":"Mid","confidence_bucket":null},"00530000000000004fce":{"cluster_role_mapped":"Bare","best_soft_norm":1.0,"uncertain":false,"flipped_this_season":false,"streak_len_current":3,"time_since_last_flip":null,"npts_total":5,"env_z_season":-0.24332623894619562,"stratum":"Mid","confidence_bucket":null},"00530000000000004fcf":{"cluster_role_mapped":"Bare","best_soft_norm":0.2583703051555229,"uncertain":false,"flipped_this_season":false,"streak_len_current":3,"time_since_last_flip":null,"npts_total":5,"env_z_season":0.28666425494962905,"stratum":"Mid","confidence_bucket":null},"00530000000000004fd0":{"cluster_role_mapped":"Bare","best_soft_norm":0.5066075890234841,"uncertain":false,"flipped_this_season":false,"streak_len_current":3,"time_since_last_flip":null,"npts_total":5,"env_z_season":-1.266992590169537,"stratum":"Mid","confidence_bucket":null},"00530000000000004fd1":{"cluster_role_mapped":"Bare","best_soft_norm":0.4962382439166536,"uncertain":false,"flipped_this_season":false,"streak_len_current":3,"time_since_last_flip":null,"npts_total":5,"env_z_season":-1.3102701504486551,"stratum":"Mid","confidence_bucket":null},"00530000000000004fd2":{"cluster_role_mapped":"Bare","best_soft_norm":0.44546594855451627,"uncertain":false,"flipped_this_season":false,"streak_len_current":3,"time_since_last_flip":null,"npts_total":5,"env_z_season":-0.936871785667536,"stratum":"Mid","confidence_bucket":null},"00530000000000004fd3":{"cluster_role_mapped":"Bare","best_soft_norm":0.9405037754985562,"uncertain":false,"flipped_this_season":false,"streak_len_current":3,"time_since_last_flip":null,"npts_total":5,"env_z_season":-0.4167816165595748,"stratum":"Mid","confidence_bucket":null},"00530000000000004fd7":{"cluster_role_mapped":"Cover","best_soft_norm":0.5994519617920843,"uncertain":false,"flipped_this_season":true,"streak_len_current":1,"time_since_last_flip":0,"npts_total":5,"env_z_season":0.5667701490909403,"stratum":"Mid","confidence_bucket":null},"00530000000000004fd8":{"cluster_role_mapped":"Bare","best_soft_norm":0.7145882238408782,"uncertain":false,"flipped_this_season":false,"streak_len_current":3,"time_since_last_flip":null,"npts_total":5,"env_z_season":-0.7657970580257665,"stratum":"Mid","confidence_bucket":null},"00530000000000004fdd":{"cluster_role_mapped":"Bare","best_soft_norm":1.0,"uncertain":false,"flipped_this_season":false,"streak_len_current":3,"time_since_last_flip":null,"npts_total":5,"env_z_season":-0.21367125174578344,"stratum":"Mid","confidence_bucket":null},"00530000000000004fe0":{"cluster_role_mapped":"Bare","best_soft_norm":0.8031581304480666,"uncertain":false,"flipped_this_season":false,"streak_len_current":3,"time_since_last_flip":null,"npts_total":5,"env_z_season":0.11502003977596997,"stratum":"Mid","confidence_bucket":null},"00530000000000004fe1":{"cluster_role_mapped":"Cover","best_soft_norm":0.035861132222451186,"uncertain":true,"flipped_this_season":true,"streak_len_current":1,"time_since_last_flip":0,"npts_total":5,"env_z_season":0.23299910975013327,"stratum":"Mid","confidence_bucket":null},"00530000000000004fe2":{"cluster_role_mapped":"Bare","best_soft_norm":0.7436736518412904,"uncertain":false,"flipped_this_season":false,"streak_len_current":3,"time_since_last_flip":null,"npts_total":5,"env_z_season":0.09896077687670927,"stratum":"Mid","confidence_bucket":null},"00530000000000004fe3":{"cluster_role_mapped":"Bare","best_soft_norm":1.0,"uncertain":false,"flipped_this_season":false,"streak_len_current":3,"time_since_last_flip":null,"npts_total":5,"env_z_season":-0.1975919587142385,"stratum":"Mid","confidence_bucket":null},"00530000000000004fe4":{"cluster_role_mapped":"Cover","best_soft_norm":0.5683337847402874,"uncertain":false,"flipped_this_season":true,"streak_len_current":1,"time_since_last_flip":0,"npts_total":5,"env_z_season":1.0091807026833544,"stratum":"Mid","confidence_bucket":null},"00530000000000004fe9":{"cluster_role_mapped":"Cover","best_soft_norm":0.21988462525995647,"uncertain":false,"flipped_this_season":false,"streak_len_current":3,"time_since_last_flip":null,"npts_total":5,"env_z_season":0.7422918788486125,"stratum":"Mid","confidence_bucket":null},"00530000000000004fea":{"cluster_role_mapped":"Cover","best_soft_norm":0.0,"uncertain":true,"flipped_this_season":false,"streak_len_current":2,"time_since_last_flip":1,"npts_total":5,"env_z_season":0.4996136383612907,"stratum":"Mid","confidence_bucket":null},"00530000000000004feb":{"cluster_role_mapped":"Bare","best_soft_norm":0.5234925642595117,"uncertain":false,"flipped_this_season":false,"streak_len_current":3,"time_since_last_flip":null,"npts_total":5,"env_z_season":-0.7874732169357976,"stratum":"Mid","confidence_bucket":null},"00530000000000004fee":{"cluster_role_mapped":"Bare","best_soft_norm":0.3199017658724136,"uncertain":false,"flipped_this_season":false,"streak_len_current":2,"time_since_last_flip":1,"npts_total":5,"env_z_season":0.09257176211372121,"stratum":"Mid","confidence_bucket":null},"00530000000000004ff0":{"cluster_role_mapped":"Bare","best_soft_norm":0.6036772688127301,"uncertain":false,"flipped_this_season":true,"streak_len_current":1,"time_since_last_flip":0,"npts_total":5,"env_z_season":0.28510765200831806,"stratum":"Mid","confidence_bucket":null},"00530000000000004ff1":{"cluster_role_mapped":"Bare","best_soft_norm":0.9730210981954271,"uncertain":false,"flipped_this_season":false,"streak_len_current":3,"time_since_last_flip":null,"npts_total":5,"env_z_season":-0.06950528548706512,"stratum":"Mid","confidence_bucket":null},"00530000000000004ff4":{"cluster_role_mapped":"Bare","best_soft_norm":0.7839121159613417,"uncertain":false,"flipped_this_season":false,"streak_len_current":3,"time_since_last_flip":null,"npts_total":5,"env_z_season":-0.6626559992627677,"stratum":"Mid","confidence_bucket":null},"00530000000000004ff6":{"cluster_role_mapped":"Cover","best_soft_norm":0.0,"uncertain":true,"flipped_this_season":true,"streak_len_current":1,"time_since_last_flip":0,"npts_total":5,"env_z_season":1.4831694509316267,"stratum":"Mid","confidence_bucket":null},"00530000000000004ff8":{"cluster_role_mapped":"Bare","best_soft_norm":0.0,"uncertain":true,"flipped_this_season":false,"streak_len_current":2,"time_since_last_flip":1,"npts_total":5,"env_z_season":0.34398637348673955,"stratum":"Mid","confidence_bucket":null},"00530000000000004ff9":{"cluster_role_mapped":"Bare","best_soft_norm":1.0,"uncertain":false,"flipped_this_season":false,"streak_len_current":3,"time_since_last_flip":null,"npts_total":5,"env_z_season":-0.12244660177195132,"stratum":"Mid","confidence_bucket":null},"00530000000000004ffa":{"cluster_role_mapped":"Bare","best_soft_norm":0.9294236339338721,"uncertain":false,"flipped_this_season":false,"streak_len_current":3,"time_since_last_flip":null,"npts_total":5,"env_z_season":-0.5803866879692471,"stratum":"Mid","confidence_bucket":null},"00530000000000004ffb":{"cluster_role_mapped":"Cover","best_soft_norm":0.02793026963433301,"uncertain":true,"flipped_this_season":true,"streak_len_current":1,"time_since_last_flip":0,"npts_total":5,"env_z_season":0.9427789671522228,"stratum":"Mid","confidence_bucket":null},"00530000000000004ffd":{"cluster_role_mapped":"Bare","best_soft_norm":0.9768663544684373,"uncertain":false,"flipped_this_season":false,"streak_len_current":3,"time_since_last_flip":null,"npts_total":5,"env_z_season":-0.0772688781853951,"stratum":"Mid","confidence_bucket":null},"00530000000000004fff":{"cluster_role_mapped":"Bare","best_soft_norm":0.5595475675252146,"uncertain":false,"flipped_this_season":false,"streak_len_current":2,"time_since_last_flip":1,"npts_total":5,"env_z_season":0.06410506212979977,"stratum":"Mid","confidence_bucket":null},"00530000000000005005":{"cluster_role_mapped":"Bare","best_soft_norm":0.18493943584534572,"uncertain":false,"flipped_this_season":false,"streak_len_current":2,"time_since_last_flip":1,"npts_total":5,"env_z_season":0.0647781865233654,"stratum":"Mid","confidence_bucket":null},"00530000000000005007":{"cluster_role_mapped":"Bare","best_soft_norm":1.0,"uncertain":false,"flipped_this_season":false,"streak_len_current":3,"time_since_last_flip":null,"npts_total":5,"env_z_season":-0.34266279967894536,"stratum":"Mid","confidence_bucket":null},"0053000000000000500f":{"cluster_role_mapped":"Cover","best_soft_norm":0.052791757000385076,"uncertain":true,"flipped_this_season":true,"streak_len_current":1,"time_since_last_flip":0,"npts_total":5,"env_z_season":1.55449859846663,"stratum":"Mid","confidence_bucket":null},"00530000000000005012":{"cluster_role_mapped":"Bare","best_soft_norm":0.8292741212529329,"uncertain":false,"flipped_this_season":false,"streak_len_current":3,"time_since_last_flip":null,"npts_total":5,"env_z_season":-0.6498523496963674,"stratum":"Mid","confidence_bucket":null},"00530000000000005017":{"cluster_role_mapped":"Cover","best_soft_norm":0.1564125766724632,"uncertain":false,"flipped_this_season":true,"streak_len_current":1,"time_since_last_flip":0,"npts_total":5,"env_z_season":1.7600498305733785,"stratum":"Mid","confidence_bucket":null},"00530000000000005018":{"cluster_role_mapped":"Cover","best_soft_norm":0.009941159979174113,"uncertain":true,"flipped_this_season":true,"streak_len_current":1,"time_since_last_flip":0,"npts_total":5,"env_z_season":0.9545428301770047,"stratum":"Mid","confidence_bucket":null},"0053000000000000501a":{"cluster_role_mapped":"Cover","best_soft_norm":0.5197450023267595,"uncertain":false,"flipped_this_season":false,"streak_len_current":3,"time_since_last_flip":null,"npts_total":5,"env_z_season":0.7248116919607482,"stratum":"Mid","confidence_bucket":null},"0053000000000000501c":{"cluster_role_mapped":"Cover","best_soft_norm":0.12465560278014848,"uncertain":true,"flipped_this_season":false,"streak_len_current":3,"time_since_last_flip":null,"npts_total":5,"env_z_season":3.0,"stratum":"Mid","confidence_bucket":null},"0053000000000000501d":{"cluster_role_mapped":"Bare","best_soft_norm":0.3832812569584786,"uncertain":false,"flipped_this_season":false,"streak_len_current":2,"time_since_last_flip":1,"npts_total":5,"env_z_season":0.24815224874483302,"stratum":"Mid","confidence_bucket":null},"0053000000000000501e":{"cluster_role_mapped":"Cover","best_soft_norm":0.0,"uncertain":true,"flipped_this_season":false,"streak_len_current":3,"time_since_last_flip":null,"npts_total":5,"env_z_season":3.0,"stratum":"Mid","confidence_bucket":null},"00530000000000005020":{"cluster_role_mapped":"Bare","best_soft_norm":0.9412374543383772,"uncertain":false,"flipped_this_season":false,"streak_len_current":3,"time_since_last_flip":null,"npts_total":5,"env_z_season":-0.4568819132345405,"stratum":"Mid","confidence_bucket":null},"00530000000000005026":{"cluster_role_mapped":"Bare","best_soft_norm":1.0,"uncertain":false,"flipped_this_season":false,"streak_len_current":3,"time_since_last_flip":null,"npts_total":5,"env_z_season":-0.3134480376124613,"stratum":"Mid","confidence_bucket":null},"00530000000000005027":{"cluster_role_mapped":"Bare","best_soft_norm":0.8114547649022654,"uncertain":false,"flipped_this_season":false,"streak_len_current":3,"time_since_last_flip":null,"npts_total":5,"env_z_season":0.0016003556713953698,"stratum":"Mid","confidence_bucket":null},"00530000000000005029":{"cluster_role_mapped":"Bare","best_soft_norm":0.17747992661123393,"uncertain":false,"flipped_this_season":false,"streak_len_current":3,"time_since_last_flip":null,"npts_total":5,"env_z_season":0.5295302744165551,"stratum":"Mid","confidence_bucket":null},"0053000000000000502e":{"cluster_role_mapped":"Bare","best_soft_norm":0.0,"uncertain":true,"flipped_this_season":false,"streak_len_current":3,"time_since_last_flip":null,"npts_total":5,"env_z_season":1.1092099801711708,"stratum":"Mid","confidence_bucket":null},"0053000000000000502f":{"cluster_role_mapped":"Bare","best_soft_norm":1.0,"uncertain":false,"flipped_this_season":false,"streak_len_current":3,"time_since_last_flip":null,"npts_total":5,"env_z_season":-0.38482649797969354,"stratum":"Mid","confidence_bucket":null},"00530000000000005032":{"cluster_role_mapped":"Bare","best_soft_norm":0.84076465907958,"uncertain":false,"flipped_this_season":false,"streak_len_current":3,"time_since_last_flip":null,"npts_total":5,"env_z_season":0.1332770343128207,"stratum":"Mid","confidence_bucket":null},"00530000000000005037":{"cluster_role_mapped":"Bare","best_soft_norm":0.37625896020034333,"uncertain":false,"flipped_this_season":false,"streak_len_current":3,"time_since_last_flip":null,"npts_total":5,"env_z_season":-1.5769387427090704,"stratum":"Mid","confidence_bucket":null},"00530000000000005038":{"cluster_role_mapped":"Bare","best_soft_norm":0.025617522433108487,"uncertain":true,"flipped_this_season":true,"streak_len_current":1,"time_since_last_flip":0,"npts_total":5,"env_z_season":0.13873681175527824,"stratum":"Mid","confidence_bucket":null},"0053000000000000503d":{"cluster_role_mapped":"Bare","best_soft_norm":0.3022419340934747,"uncertain":false,"flipped_this_season":false,"streak_len_current":2,"time_since_last_flip":1,"npts_total":5,"env_z_season":-2.094600637563952,"stratum":"Mid","confidence_bucket":null},"0053000000000000503e":{"cluster_role_mapped":"Bare","best_soft_norm":1.0,"uncertain":false,"flipped_this_season":false,"streak_len_current":3,"time_since_last_flip":null,"npts_total":5,"env_z_season":-0.3658145169618544,"stratum":"Mid","confidence_bucket":null},"0053000000000000503f":{"cluster_role_mapped":"Bare","best_soft_norm":0.12660636822700388,"uncertain":true,"flipped_this_season":false,"streak_len_current":3,"time_since_last_flip":null,"npts_total":5,"env_z_season":0.8669280100274092,"stratum":"Mid","confidence_bucket":null},"00530000000000005040":{"cluster_role_mapped":"Bare","best_soft_norm":0.8359810366118378,"uncertain":false,"flipped_this_season":false,"streak_len_current":3,"time_since_last_flip":null,"npts_total":5,"env_z_season":0.11966216318698675,"stratum":"Mid","confidence_bucket":null},"00530000000000005041":{"cluster_role_mapped":"Bare","best_soft_norm":0.6870198733927283,"uncertain":false,"flipped_this_season":false,"streak_len_current":3,"time_since_last_flip":null,"npts_total":5,"env_z_season":-0.10022813209098452,"stratum":"Mid","confidence_bucket":null},"00530000000000005042":{"cluster_role_mapped":"Bare","best_soft_norm":0.8876529006323639,"uncertain":false,"flipped_this_season":false,"streak_len_current":3,"time_since_last_flip":null,"npts_total":5,"env_z_season":-0.6061603784703438,"stratum":"Mid","confidence_bucket":null},"00530000000000005045":{"cluster_role_mapped":"Cover","best_soft_norm":0.0,"uncertain":true,"flipped_this_season":true,"streak_len_current":1,"time_since_last_flip":0,"npts_total":5,"env_z_season":-0.3556487643004263,"stratum":"Mid","confidence_bucket":null},"0053000000000000504b":{"cluster_role_mapped":"Bare","best_soft_norm":0.17580383077999903,"uncertain":false,"flipped_this_season":false,"streak_len_current":3,"time_since_last_flip":null,"npts_total":5,"env_z_season":0.7615784606909629,"stratum":"Mid","confidence_bucket":null},"0053000000000000504c":{"cluster_role_mapped":"Bare","best_soft_norm":0.0,"uncertain":true,"flipped_this_season":false,"streak_len_current":3,"time_since_last_flip":null,"npts_total":5,"env_z_season":0.7234295690583059,"stratum":"Mid","confidence_bucket":null},"0053000000000000504e":{"cluster_role_mapped":"Bare","best_soft_norm":0.938572157427096,"uncertain":false,"flipped_this_season":false,"streak_len_current":3,"time_since_last_flip":null,"npts_total":5,"env_z_season":-0.4333604720752869,"stratum":"Mid","confidence_bucket":null},"00530000000000005059":{"cluster_role_mapped":"Bare","best_soft_norm":0.547743412922922,"uncertain":false,"flipped_this_season":false,"streak_len_current":3,"time_since_last_flip":null,"npts_total":5,"env_z_season":0.33994818481145306,"stratum":"Mid","confidence_bucket":null},"0053000000000000505b":{"cluster_role_mapped":"Bare","best_soft_norm":0.24598644257173288,"uncertain":false,"flipped_this_season":false,"streak_len_current":3,"time_since_last_flip":null,"npts_total":5,"env_z_season":0.5364216736470159,"stratum":"Mid","confidence_bucket":null},"0053000000000000505d":{"cluster_role_mapped":"Bare","best_soft_norm":0.9963413740803467,"uncertain":false,"flipped_this_season":false,"streak_len_current":3,"time_since_last_flip":null,"npts_total":5,"env_z_season":0.03443713305562269,"stratum":"Mid","confidence_bucket":null},"00530000000000005066":{"cluster_role_mapped":"Bare","best_soft_norm":0.7295761208727858,"uncertain":false,"flipped_this_season":true,"streak_len_current":1,"time_since_last_flip":0,"npts_total":5,"env_z_season":-0.8259136351568288,"stratum":"Mid","confidence_bucket":null},"00530000000000005068":{"cluster_role_mapped":"Bare","best_soft_norm":0.9571424707947342,"uncertain":false,"flipped_this_season":true,"streak_len_current":1,"time_since_last_flip":0,"npts_total":5,"env_z_season":-0.5553356901082269,"stratum":"Mid","confidence_bucket":null},"0053000000000000506a":{"cluster_role_mapped":"Bare","best_soft_norm":1.0,"uncertain":false,"flipped_this_season":true,"streak_len_current":1,"time_since_last_flip":0,"npts_total":5,"env_z_season":-0.34798440029005906,"stratum":"Mid","confidence_bucket":null},"0053000000000000506c":{"cluster_role_mapped":"Bare","best_soft_norm":1.0,"uncertain":false,"flipped_this_season":false,"streak_len_current":3,"time_since_last_flip":null,"npts_total":5,"env_z_season":-0.12414616493110449,"stratum":"Mid","confidence_bucket":null},"00530000000000005075":{"cluster_role_mapped":"Bare","best_soft_norm":0.23622449639152146,"uncertain":false,"flipped_this_season":true,"streak_len_current":1,"time_since_last_flip":0,"npts_total":5,"env_z_season":0.6349968674499162,"stratum":"Mid","confidence_bucket":null},"00530000000000005078":{"cluster_role_mapped":"Bare","best_soft_norm":0.14388020896816964,"uncertain":true,"flipped_this_season":false,"streak_len_current":3,"time_since_last_flip":null,"npts_total":5,"env_z_season":-0.905625767082901,"stratum":"Mid","confidence_bucket":null},"00530000000000005079":{"cluster_role_mapped":"Bare","best_soft_norm":0.28344792406783054,"uncertain":false,"flipped_this_season":false,"streak_len_current":3,"time_since_last_flip":null,"npts_total":5,"env_z_season":0.574527440924276,"stratum":"Mid","confidence_bucket":null},"0053000000000000507a":{"cluster_role_mapped":"Bare","best_soft_norm":0.8885678835473914,"uncertain":false,"flipped_this_season":false,"streak_len_current":3,"time_since_last_flip":null,"npts_total":5,"env_z_season":-0.49955975739446723,"stratum":"Mid","confidence_bucket":null},"00530000000000005080":{"cluster_role_mapped":"Bare","best_soft_norm":0.3098603483533303,"uncertain":false,"flipped_this_season":false,"streak_len_current":3,"time_since_last_flip":null,"npts_total":5,"env_z_season":0.5676654537627616,"stratum":"Mid","confidence_bucket":null},"00530000000000005081":{"cluster_role_mapped":"Bare","best_soft_norm":0.0,"uncertain":true,"flipped_this_season":false,"streak_len_current":2,"time_since_last_flip":1,"npts_total":5,"env_z_season":0.6834644488434801,"stratum":"Mid","confidence_bucket":null},"00530000000000005093":{"cluster_role_mapped":"Cover","best_soft_norm":0.0,"uncertain":true,"flipped_this_season":true,"streak_len_current":1,"time_since_last_flip":0,"npts_total":5,"env_z_season":0.8250573310579398,"stratum":"Mid","confidence_bucket":null},"00530000000000005105":{"cluster_role_mapped":"Bare","best_soft_norm":0.5217903095717482,"uncertain":false,"flipped_this_season":false,"streak_len_current":3,"time_since_last_flip":null,"npts_total":5,"env_z_season":-0.09613513144573486,"stratum":"Mid","confidence_bucket":null},"00530000000000005106":{"cluster_role_mapped":"Bare","best_soft_norm":0.3616297714980898,"uncertain":false,"flipped_this_season":false,"streak_len_current":3,"time_since_last_flip":null,"npts_total":5,"env_z_season":0.08217529293508244,"stratum":"Mid","confidence_bucket":null},"00530000000000005107":{"cluster_role_mapped":"Bare","best_soft_norm":0.7795117374699146,"uncertain":false,"flipped_this_season":false,"streak_len_current":3,"time_since_last_flip":null,"npts_total":5,"env_z_season":0.1688476305527005,"stratum":"Mid","confidence_bucket":null},"00530000000000005108":{"cluster_role_mapped":"Bare","best_soft_norm":0.30390303558992937,"uncertain":false,"flipped_this_season":false,"streak_len_current":2,"time_since_last_flip":1,"npts_total":5,"env_z_season":0.5876027059686408,"stratum":"Mid","confidence_bucket":null},"00530000000000005109":{"cluster_role_mapped":"Bare","best_soft_norm":0.0,"uncertain":true,"flipped_this_season":false,"streak_len_current":2,"time_since_last_flip":1,"npts_total":5,"env_z_season":0.2902528616465325,"stratum":"Mid","confidence_bucket":null},"0053000000000000510a":{"cluster_role_mapped":"Bare","best_soft_norm":0.0,"uncertain":true,"flipped_this_season":false,"streak_len_current":2,"time_since_last_flip":1,"npts_total":5,"env_z_season":0.06652799356975142,"stratum":"Mid","confidence_bucket":null},"005300000000000052cc":{"cluster_role_mapped":"Bare","best_soft_norm":0.7128587873099681,"uncertain":false,"flipped_this_season":false,"streak_len_current":3,"time_since_last_flip":null,"npts_total":5,"env_z_season":-0.2516212830071017,"stratum":"Mid","confidence_bucket":null},"005300000000000052d1":{"cluster_role_mapped":"Cover","best_soft_norm":0.009378293563391774,"uncertain":true,"flipped_this_season":false,"streak_len_current":3,"time_since_last_flip":null,"npts_total":5,"env_z_season":3.0,"stratum":"Mid","confidence_bucket":null},"00530000000000005313":{"cluster_role_mapped":"Bare","best_soft_norm":0.5319276771786775,"uncertain":false,"flipped_this_season":false,"streak_len_current":3,"time_since_last_flip":null,"npts_total":5,"env_z_season":-0.12096221367305142,"stratum":"Mid","confidence_bucket":null},"00530000000000005316":{"cluster_role_mapped":"Bare","best_soft_norm":0.07222545580779964,"uncertain":true,"flipped_this_season":false,"streak_len_current":2,"time_since_last_flip":1,"npts_total":5,"env_z_season":-0.40808337719299936,"stratum":"Mid","confidence_bucket":null},"00530000000000005347":{"cluster_role_mapped":"Cover","best_soft_norm":0.7231791194931453,"uncertain":false,"flipped_this_season":true,"streak_len_current":1,"time_since_last_flip":0,"npts_total":5,"env_z_season":0.7209656384182703,"stratum":"Mid","confidence_bucket":null},"0053000000000000534a":{"cluster_role_mapped":"Bare","best_soft_norm":0.38073983182791593,"uncertain":false,"flipped_this_season":true,"streak_len_current":1,"time_since_last_flip":0,"npts_total":5,"env_z_season":0.33967826069442497,"stratum":"Mid","confidence_bucket":null},"0053000000000000534b":{"cluster_role_mapped":"Bare","best_soft_norm":0.5881550948697845,"uncertain":false,"flipped_this_season":false,"streak_len_current":3,"time_since_last_flip":null,"npts_total":5,"env_z_season":0.31149356653469434,"stratum":"Mid","confidence_bucket":null},"0053000000000000534d":{"cluster_role_mapped":"Bare","best_soft_norm":1.0,"uncertain":false,"flipped_this_season":false,"streak_len_current":3,"time_since_last_flip":null,"npts_total":5,"env_z_season":-0.05896283962193872,"stratum":"Mid","confidence_bucket":null},"0053000000000000535c":{"cluster_role_mapped":"Bare","best_soft_norm":0.9003244877748017,"uncertain":false,"flipped_this_season":false,"streak_len_current":3,"time_since_last_flip":null,"npts_total":5,"env_z_season":-0.13754298964270747,"stratum":"Mid","confidence_bucket":null},"0053000000000000535d":{"cluster_role_mapped":"Bare","best_soft_norm":0.8089491099643934,"uncertain":false,"flipped_this_season":false,"streak_len_current":3,"time_since_last_flip":null,"npts_total":5,"env_z_season":0.1421858987630685,"stratum":"Mid","confidence_bucket":null},"00530000000000005380":{"cluster_role_mapped":"Bare","best_soft_norm":0.5776876636101728,"uncertain":false,"flipped_this_season":false,"streak_len_current":3,"time_since_last_flip":null,"npts_total":5,"env_z_season":-0.43881093980452396,"stratum":"Mid","confidence_bucket":null},"00530000000000005381":{"cluster_role_mapped":"Bare","best_soft_norm":0.7151437115638886,"uncertain":false,"flipped_this_season":false,"streak_len_current":3,"time_since_last_flip":null,"npts_total":5,"env_z_season":-0.48056197566670283,"stratum":"Mid","confidence_bucket":null},"00530000000000005399":{"cluster_role_mapped":"Bare","best_soft_norm":0.45106882112065044,"uncertain":false,"flipped_this_season":false,"streak_len_current":2,"time_since_last_flip":1,"npts_total":5,"env_z_season":0.23871569839597634,"stratum":"Mid","confidence_bucket":null},"0053000000000000539a":{"cluster_role_mapped":"Bare","best_soft_norm":0.437981412706842,"uncertain":false,"flipped_this_season":false,"streak_len_current":3,"time_since_last_flip":null,"npts_total":5,"env_z_season":0.32523537879532777,"stratum":"Mid","confidence_bucket":null},"0053000000000000539b":{"cluster_role_mapped":"Bare","best_soft_norm":0.44631769051502207,"uncertain":false,"flipped_this_season":false,"streak_len_current":2,"time_since_last_flip":1,"npts_total":5,"env_z_season":0.2634058998714311,"stratum":"Mid","confidence_bucket":null},"0053000000000000539c":{"cluster_role_mapped":"Bare","best_soft_norm":0.5361045948238436,"uncertain":false,"flipped_this_season":false,"streak_len_current":3,"time_since_last_flip":null,"npts_total":5,"env_z_season":0.023498522682617092,"stratum":"Mid","confidence_bucket":null},"0053000000000000539d":{"cluster_role_mapped":"Bare","best_soft_norm":0.4898125135262564,"uncertain":false,"flipped_this_season":false,"streak_len_current":3,"time_since_last_flip":null,"npts_total":5,"env_z_season":0.1910816854839856,"stratum":"Mid","confidence_bucket":null},"00590000000000009b30":{"cluster_role_mapped":"Bare","best_soft_norm":0.965794628725428,"uncertain":false,"flipped_this_season":false,"streak_len_current":3,"time_since_last_flip":null,"npts_total":5,"env_z_season":-0.4561874300633485,"stratum":"Mid","confidence_bucket":null},"00590000000000009b31":{"cluster_role_mapped":"Bare","best_soft_norm":0.8487363661688128,"uncertain":false,"flipped_this_season":false,"streak_len_current":3,"time_since_last_flip":null,"npts_total":5,"env_z_season":-0.36781515767975304,"stratum":"Mid","confidence_bucket":null},"00590000000000009b32":{"cluster_role_mapped":"Bare","best_soft_norm":0.8322300902073665,"uncertain":false,"flipped_this_season":false,"streak_len_current":3,"time_since_last_flip":null,"npts_total":5,"env_z_season":-0.45751898038206723,"stratum":"Mid","confidence_bucket":null},"00590000000000009b33":{"cluster_role_mapped":"Bare","best_soft_norm":1.0,"uncertain":false,"flipped_this_season":false,"streak_len_current":3,"time_since_last_flip":null,"npts_total":5,"env_z_season":-0.34664913315915685,"stratum":"Mid","confidence_bucket":null},"00590000000000009b34":{"cluster_role_mapped":"Bare","best_soft_norm":0.844429553645025,"uncertain":false,"flipped_this_season":false,"streak_len_current":3,"time_since_last_flip":null,"npts_total":5,"env_z_season":-0.42501999803317503,"stratum":"Mid","confidence_bucket":null},"00590000000000009b37":{"cluster_role_mapped":"Cover","best_soft_norm":0.4506606205892817,"uncertain":false,"flipped_this_season":false,"streak_len_current":2,"time_since_last_flip":1,"npts_total":5,"env_z_season":1.063859848391169,"stratum":"Mid","confidence_bucket":null}}